odoo/addons/purchase_order_partner_manual_rank/README.rst
odoo/addons/purchase_order_partner_manual_rank/__init__.py
odoo/addons/purchase_order_partner_manual_rank/__manifest__.py
odoo/addons/purchase_order_partner_manual_rank/i18n/it.po
odoo/addons/purchase_order_partner_manual_rank/i18n/purchase_order_partner_manual_rank.pot
odoo/addons/purchase_order_partner_manual_rank/readme/CONTRIBUTORS.rst
odoo/addons/purchase_order_partner_manual_rank/readme/DESCRIPTION.rst
odoo/addons/purchase_order_partner_manual_rank/readme/USAGE.rst
odoo/addons/purchase_order_partner_manual_rank/static/description/icon.png
odoo/addons/purchase_order_partner_manual_rank/static/description/index.html
odoo/addons/purchase_order_partner_manual_rank/views/product_supplierinfo_views.xml
odoo/addons/purchase_order_partner_manual_rank/views/purchase_order_views.xml
odoo14_addon_purchase_order_partner_manual_rank-14.0.2.0.0.dist-info/METADATA
odoo14_addon_purchase_order_partner_manual_rank-14.0.2.0.0.dist-info/WHEEL
odoo14_addon_purchase_order_partner_manual_rank-14.0.2.0.0.dist-info/top_level.txt
odoo14_addon_purchase_order_partner_manual_rank-14.0.2.0.0.dist-info/RECORD
